fastapi_namespace/__init__.py
fastapi_namespace/namespace.py
fastapi_namespace/resource.py
fastapi_namespace/types.py
fastapi_namespace/typings.py
fastapi_namespace/utils.py
fastapi_namespace/mixins/__init__.py
fastapi_namespace/mixins/mixinBase.py
fastapi_namespace/mixins/token/__init__.py
fastapi_namespace/mixins/token/base.py
fastapi_namespace/mixins/token/jwtTokenMixin.py
fastapi_namespace/mixins/token/opaqueTokenMixin.py
fastapi_namespace/mixins/token/tokenBaseMixin.py
fastapi_namespace/mixins/token/typings.py
fastapi_namespace/mixins/token/utils.py
fastapi_namespace/mixins/token/sercurity/__init__.py
fastapi_namespace/mixins/token/sercurity/base.py
fastapi_namespace/mixins/token/sercurity/oauth2.py
fastapi_namespace/tests/__init__.py
fastapi_namespace/tests/test.py
fastapi_namespace/tests/test2.py
fastapi_namespace/tests/test3.py
fastapi_namespace/tests/test4.py
fastapi_namespace_vet1ments-0.1.15.dist-info/LICENSE
fastapi_namespace_vet1ments-0.1.15.dist-info/METADATA
fastapi_namespace_vet1ments-0.1.15.dist-info/WHEEL
fastapi_namespace_vet1ments-0.1.15.dist-info/top_level.txt
fastapi_namespace_vet1ments-0.1.15.dist-info/RECORD
