Metadata-Version: 2.1
Name: fastapi-namespace-vet1ments
Version: 0.1.15
Summary: For FastAPI Routing Class
Author: no hong seok
Author-email: vet1ments@naver.com
Maintainer: no hong seok
Maintainer-email: vet1ments@naver.com
License: MIT
Project-URL: Repository, https://github.com/vet1ments/fastapi_namespace
Requires-Python: >=3.11.0
License-File: LICENSE
Requires-Dist: fastapi>=0.108.0
